ehsaneddintk/__init__.py
ehsaneddintk/fileutil/__init__.py
ehsaneddintk/fileutil/fileutil.py
ehsaneddintk/math/__init__.py
ehsaneddintk/visualization/__init__.py
ehsantk-0.1.0.dist-info/LICENSE
ehsantk-0.1.0.dist-info/METADATA
ehsantk-0.1.0.dist-info/WHEEL
ehsantk-0.1.0.dist-info/top_level.txt
ehsantk-0.1.0.dist-info/RECORD
